odoo/addons/l10n_th_account_tax_expense_operating_unit/README.rst
odoo/addons/l10n_th_account_tax_expense_operating_unit/__init__.py
odoo/addons/l10n_th_account_tax_expense_operating_unit/__manifest__.py
odoo/addons/l10n_th_account_tax_expense_operating_unit/i18n/l10n_th_account_tax_expense_operating_unit.pot
odoo/addons/l10n_th_account_tax_expense_operating_unit/models/__init__.py
odoo/addons/l10n_th_account_tax_expense_operating_unit/models/hr_expense_sheet.py
odoo/addons/l10n_th_account_tax_expense_operating_unit/readme/CONTRIBUTORS.rst
odoo/addons/l10n_th_account_tax_expense_operating_unit/readme/DESCRIPTION.rst
odoo/addons/l10n_th_account_tax_expense_operating_unit/static/description/icon.png
odoo/addons/l10n_th_account_tax_expense_operating_unit/static/description/index.html
odoo/addons/l10n_th_account_tax_expense_operating_unit/tests/__init__.py
odoo/addons/l10n_th_account_tax_expense_operating_unit/tests/test_expense_wht_operating_unit.py
odoo_addon_l10n_th_account_tax_expense_operating_unit-15.0.1.0.0.1.dist-info/METADATA
odoo_addon_l10n_th_account_tax_expense_operating_unit-15.0.1.0.0.1.dist-info/WHEEL
odoo_addon_l10n_th_account_tax_expense_operating_unit-15.0.1.0.0.1.dist-info/top_level.txt
odoo_addon_l10n_th_account_tax_expense_operating_unit-15.0.1.0.0.1.dist-info/RECORD
