Metadata-Version: 2.1
Name: odoo-addon-l10n-th-account-tax-expense-operating-unit
Version: 15.0.1.0.0.1
Summary: Thai Localization - Expense Tax Operating Unit
Home-page: https://github.com/OCA/l10n-thailand
Author: Ecosoft, Odoo Community Association (OCA)
Author-email: support@odoo-community.org
License: AGPL-3
Platform: UNKNOWN
Classifier: Programming Language :: Python
Classifier: Framework :: Odoo
Classifier: Framework :: Odoo :: 15.0
Classifier: License :: OSI Approved :: GNU Affero General Public License v3
Requires-Python: >=3.8
Requires-Dist: odoo-addon-hr-expense-operating-unit <15.1dev,>=15.0dev
Requires-Dist: odoo-addon-l10n-th-account-tax-expense <15.1dev,>=15.0dev
Requires-Dist: odoo <15.1dev,>=15.0a
